DSD_midterm_400104867/4 -FPmultiplier/Multiplier.v
module Multiplication
#( 
    parameter frac_bits =23 ,
    parameter exp_bits = 8 
)
(
    input [exp_bits+frac_bits:0] a,
    input [exp_bits+frac_bits:0] b,
    output exception,
    output overflow,
    output underflow,
    output [exp_bits+frac_bits:0] res
);


wire sign,round,normalised,zero;
wire [exp_bits:0] exponent,sum_exponent;
wire [frac_bits - 1 :0] product_mantissa;
wire [frac_bits :0] op_a,op_b;  // inja ye yek ya sefr mizarim baghal mantisa
wire [2 * (frac_bits + 1) - 1:0] product , product_normalised; 


assign sign = a[frac_bits + exp_bits] ^ b[frac_bits + exp_bits];				
assign exception = (&a[frac_bits + exp_bits - 1 :frac_bits]) | (&b[frac_bits + exp_bits -1:frac_bits]);//111....11 = NAN bayad error dad

assign op_a = (|a[frac_bits + exp_bits - 1 :frac_bits]) ? {1'b1,a[frac_bits - 1 :0]} : {1'b0,a[frac_bits - 1 :0]};
assign op_b = (|b[frac_bits + exp_bits - 1 :frac_bits]) ? {1'b1,b[frac_bits - 1 :0]} : {1'b0,b[frac_bits - 1 :0]};

// alan op_a op_b ba tavajoh be denormiliza ya halat adi sakhte shodan va bayad zarb beshan

assign product = op_a * op_b;

assign normalised = product[2 * (frac_bits + 1) - 1] ? 1'b1 : 1'b0;	
//age yek bashe bayad frac taye 1 + 23bi(frac) + 24 bit round 
//age 0 bashe --> 0 + X. 23 bit(frac) + 23 bit round
assign product_normalised = normalised ? product : product << 1;
// alan kolan bayad X. 23 bit(frac) + 24(frac + 1) bit round berim 
assign round = |product_normalised[frac_bits:0]; //frac bit ya frac bit -1 SHAK DARAM DEBUG SHOD

assign product_mantissa = product_normalised[2 * (frac_bits ) :frac_bits + 1] + (product_normalised[frac_bits] & round); 	
 

assign zero = exception ? 1'b0 : (product_mantissa == {frac_bits{1'b0}}) ? 1'b1 : 1'b0;

assign sum_exponent = a[frac_bits + exp_bits -1 :frac_bits] + b[frac_bits + exp_bits -1 :frac_bits];
// jam zadan exp

assign exponent = sum_exponent - ({1'b0, {(exp_bits-1){1'b1}} }) + normalised;
//jam ke mizani - 127 ya 2 ^frac -1 -1 bayad bokoni age ham normalaie bood bekhatere yedoone shift in yedoone ziad mishe

assign overflow = ((exponent[exp_bits] & !exponent[exp_bits-1]) & !zero) ;
// bish az 255 beshe ke ja nemishe to exp
assign underflow = ((exponent[exp_bits] & exponent[exp_bits-1]) & !zero) ? 1'b1 : 1'b0;
//jam Exp ha kamtar az 127(2^frac-1 -1) --> underflow 

assign res = exception ? {(frac_bits + exp_bits +1) {1'b0}} : zero ? {{(frac_bits + exp_bits + 1) {1'b0}}} : overflow ? {sign,{exp_bits{1'b1}},{frac_bits{1'b0}} } : underflow ? {sign,{(frac_bits + exp_bits) {1'b0}}} : {sign,exponent[exp_bits - 1:0],product_mantissa};



endmodule

module TestBench;

// 32 bit be shekl 8 exp 23 frac test mikonim vali har chiz dige i ham ghabel teste
reg [31:0] a,b;
wire exception,overflow,underflow;
wire [31:0] res;

reg clk = 1'b1;

Multiplication #(.exp_bits(8),.frac_bits(23)) multiplier (a,b,exception,overflow,underflow,res);



initial
begin
$dumpfile("Fp_mult.vcd");
$dumpvars(0, TestBench);
end

initial
begin

test (32'hC2AEDFBE,32'h430F8F5C,32'hC64421D2);
//143.56 * -87.437 = -12552.455

test (32'h436A58BB,32'h3B83126F,32'h3F6FF88F);
// 234.3466 * 0.004 = 0.93738645

test (32'h4234851F,32'h427C851F,32'h453210EA);
// 45.13 * 63.13 = 2849.0571;

test (32'h4049999A,32'hC1663D71,32'hC2355063);
//3.15 * -14.39 = -45.328503

test (32'hC1526666,32'hC240A3D7,32'h441E5374);
//-13.15 * -48.16 = 633.30396

test (32'h00000000,32'h00000000,32'h00000000);
// 0 * 0 = 0;

test (32'hC1526666,32'h00000000,32'h00000000);
//-13.15 * 0 = 0;

test (32'h7F800000,32'h7F800000,32'h00000000); 
// Inf * Inf = Inf

test (32'h3089705F,32'h3089705F,32'h219392EE);
//1E-9 * 1E-9 = 9.999999E-19

test (32'h60AD78EC,32'h7E967699,32'h7F800000);
//1E20 * 1E38 = inf


test (32'h60AD78EC,32'h7E967699,32'h7F800000);
//1E20 * 1E38 = inf

$stop;

end

task test(
input [31:0] op_a,op_b,expected_Res
);
begin
	a = op_a;
	b = op_b;
    #10;
  //  $display("BINARY : \n");
 //	$display ("Run :a = %b , b = %b \n Result = %b \n expected result = %b, \n  Exception = %d,  Overflow = %d,   Underflow = %d  \n ",a,b,res,expected_Res,exception,overflow,underflow);
    $display("HEX : \n");
    $display ("Run :a = %h , b = %h \n Result = %h \n expected result = %h, \n  Exception = %d,  Overflow = %d,   Underflow = %d  \n ",a,b,res,expected_Res,exception,overflow,underflow);
    if (expected_Res == res)
        $display("True answer");
    else
        $display("False answer");
end
endtask

endmodule

DSD_midterm_400104867/4 -FPmultiplier/Fp_mult.vcd
$date
	Sun May 28 16:18:11 2023
$end
$version
	ModelSim Version 2020.4
$end
$timescale
	1ns
$end

$scope module TestBench $end
$var reg 32 ! a [31:0] $end
$var reg 32 " b [31:0] $end
$var wire 1 # exception $end
$var wire 1 $ overflow $end
$var wire 1 % underflow $end
$var wire 1 & res [31] $end
$var wire 1 ' res [30] $end
$var wire 1 ( res [29] $end
$var wire 1 ) res [28] $end
$var wire 1 * res [27] $end
$var wire 1 + res [26] $end
$var wire 1 , res [25] $end
$var wire 1 - res [24] $end
$var wire 1 . res [23] $end
$var wire 1 / res [22] $end
$var wire 1 0 res [21] $end
$var wire 1 1 res [20] $end
$var wire 1 2 res [19] $end
$var wire 1 3 res [18] $end
$var wire 1 4 res [17] $end
$var wire 1 5 res [16] $end
$var wire 1 6 res [15] $end
$var wire 1 7 res [14] $end
$var wire 1 8 res [13] $end
$var wire 1 9 res [12] $end
$var wire 1 : res [11] $end
$var wire 1 ; res [10] $end
$var wire 1 < res [9] $end
$var wire 1 = res [8] $end
$var wire 1 > res [7] $end
$var wire 1 ? res [6] $end
$var wire 1 @ res [5] $end
$var wire 1 A res [4] $end
$var wire 1 B res [3] $end
$var wire 1 C res [2] $end
$var wire 1 D res [1] $end
$var wire 1 E res [0] $end
$var reg 1 F clk $end

$scope task test $end
$var reg 32 G op_a [31:0] $end
$var reg 32 H op_b [31:0] $end
$var reg 32 I expected_Res [31:0] $end
$upscope $end

$scope module multiplier $end
$var parameter 32 J frac_bits $end
$var parameter 32 K exp_bits $end
$var wire 1 L a [31] $end
$var wire 1 M a [30] $end
$var wire 1 N a [29] $end
$var wire 1 O a [28] $end
$var wire 1 P a [27] $end
$var wire 1 Q a [26] $end
$var wire 1 R a [25] $end
$var wire 1 S a [24] $end
$var wire 1 T a [23] $end
$var wire 1 U a [22] $end
$var wire 1 V a [21] $end
$var wire 1 W a [20] $end
$var wire 1 X a [19] $end
$var wire 1 Y a [18] $end
$var wire 1 Z a [17] $end
$var wire 1 [ a [16] $end
$var wire 1 \ a [15] $end
$var wire 1 ] a [14] $end
$var wire 1 ^ a [13] $end
$var wire 1 _ a [12] $end
$var wire 1 ` a [11] $end
$var wire 1 a a [10] $end
$var wire 1 b a [9] $end
$var wire 1 c a [8] $end
$var wire 1 d a [7] $end
$var wire 1 e a [6] $end
$var wire 1 f a [5] $end
$var wire 1 g a [4] $end
$var wire 1 h a [3] $end
$var wire 1 i a [2] $end
$var wire 1 j a [1] $end
$var wire 1 k a [0] $end
$var wire 1 l b [31] $end
$var wire 1 m b [30] $end
$var wire 1 n b [29] $end
$var wire 1 o b [28] $end
$var wire 1 p b [27] $end
$var wire 1 q b [26] $end
$var wire 1 r b [25] $end
$var wire 1 s b [24] $end
$var wire 1 t b [23] $end
$var wire 1 u b [22] $end
$var wire 1 v b [21] $end
$var wire 1 w b [20] $end
$var wire 1 x b [19] $end
$var wire 1 y b [18] $end
$var wire 1 z b [17] $end
$var wire 1 { b [16] $end
$var wire 1 | b [15] $end
$var wire 1 } b [14] $end
$var wire 1 ~ b [13] $end
$var wire 1 !! b [12] $end
$var wire 1 "! b [11] $end
$var wire 1 #! b [10] $end
$var wire 1 $! b [9] $end
$var wire 1 %! b [8] $end
$var wire 1 &! b [7] $end
$var wire 1 '! b [6] $end
$var wire 1 (! b [5] $end
$var wire 1 )! b [4] $end
$var wire 1 *! b [3] $end
$var wire 1 +! b [2] $end
$var wire 1 ,! b [1] $end
$var wire 1 -! b [0] $end
$var wire 1 # exception $end
$var wire 1 $ overflow $end
$var wire 1 % underflow $end
$var wire 1 & res [31] $end
$var wire 1 ' res [30] $end
$var wire 1 ( res [29] $end
$var wire 1 ) res [28] $end
$var wire 1 * res [27] $end
$var wire 1 + res [26] $end
$var wire 1 , res [25] $end
$var wire 1 - res [24] $end
$var wire 1 . res [23] $end
$var wire 1 / res [22] $end
$var wire 1 0 res [21] $end
$var wire 1 1 res [20] $end
$var wire 1 2 res [19] $end
$var wire 1 3 res [18] $end
$var wire 1 4 res [17] $end
$var wire 1 5 res [16] $end
$var wire 1 6 res [15] $end
$var wire 1 7 res [14] $end
$var wire 1 8 res [13] $end
$var wire 1 9 res [12] $end
$var wire 1 : res [11] $end
$var wire 1 ; res [10] $end
$var wire 1 < res [9] $end
$var wire 1 = res [8] $end
$var wire 1 > res [7] $end
$var wire 1 ? res [6] $end
$var wire 1 @ res [5] $end
$var wire 1 A res [4] $end
$var wire 1 B res [3] $end
$var wire 1 C res [2] $end
$var wire 1 D res [1] $end
$var wire 1 E res [0] $end
$var wire 1 .! sign $end
$var wire 1 /! round $end
$var wire 1 0! normalised $end
$var wire 1 1! zero $end
$var wire 1 2! exponent [8] $end
$var wire 1 3! exponent [7] $end
$var wire 1 4! exponent [6] $end
$var wire 1 5! exponent [5] $end
$var wire 1 6! exponent [4] $end
$var wire 1 7! exponent [3] $end
$var wire 1 8! exponent [2] $end
$var wire 1 9! exponent [1] $end
$var wire 1 :! exponent [0] $end
$var wire 1 ;! sum_exponent [8] $end
$var wire 1 <! sum_exponent [7] $end
$var wire 1 =! sum_exponent [6] $end
$var wire 1 >! sum_exponent [5] $end
$var wire 1 ?! sum_exponent [4] $end
$var wire 1 @! sum_exponent [3] $end
$var wire 1 A! sum_exponent [2] $end
$var wire 1 B! sum_exponent [1] $end
$var wire 1 C! sum_exponent [0] $end
$var wire 1 D! product_mantissa [22] $end
$var wire 1 E! product_mantissa [21] $end
$var wire 1 F! product_mantissa [20] $end
$var wire 1 G! product_mantissa [19] $end
$var wire 1 H! product_mantissa [18] $end
$var wire 1 I! product_mantissa [17] $end
$var wire 1 J! product_mantissa [16] $end
$var wire 1 K! product_mantissa [15] $end
$var wire 1 L! product_mantissa [14] $end
$var wire 1 M! product_mantissa [13] $end
$var wire 1 N! product_mantissa [12] $end
$var wire 1 O! product_mantissa [11] $end
$var wire 1 P! product_mantissa [10] $end
$var wire 1 Q! product_mantissa [9] $end
$var wire 1 R! product_mantissa [8] $end
$var wire 1 S! product_mantissa [7] $end
$var wire 1 T! product_mantissa [6] $end
$var wire 1 U! product_mantissa [5] $end
$var wire 1 V! product_mantissa [4] $end
$var wire 1 W! product_mantissa [3] $end
$var wire 1 X! product_mantissa [2] $end
$var wire 1 Y! product_mantissa [1] $end
$var wire 1 Z! product_mantissa [0] $end
$var wire 1 [! op_a [23] $end
$var wire 1 \! op_a [22] $end
$var wire 1 ]! op_a [21] $end
$var wire 1 ^! op_a [20] $end
$var wire 1 _! op_a [19] $end
$var wire 1 `! op_a [18] $end
$var wire 1 a! op_a [17] $end
$var wire 1 b! op_a [16] $end
$var wire 1 c! op_a [15] $end
$var wire 1 d! op_a [14] $end
$var wire 1 e! op_a [13] $end
$var wire 1 f! op_a [12] $end
$var wire 1 g! op_a [11] $end
$var wire 1 h! op_a [10] $end
$var wire 1 i! op_a [9] $end
$var wire 1 j! op_a [8] $end
$var wire 1 k! op_a [7] $end
$var wire 1 l! op_a [6] $end
$var wire 1 m! op_a [5] $end
$var wire 1 n! op_a [4] $end
$var wire 1 o! op_a [3] $end
$var wire 1 p! op_a [2] $end
$var wire 1 q! op_a [1] $end
$var wire 1 r! op_a [0] $end
$var wire 1 s! op_b [23] $end
$var wire 1 t! op_b [22] $end
$var wire 1 u! op_b [21] $end
$var wire 1 v! op_b [20] $end
$var wire 1 w! op_b [19] $end
$var wire 1 x! op_b [18] $end
$var wire 1 y! op_b [17] $end
$var wire 1 z! op_b [16] $end
$var wire 1 {! op_b [15] $end
$var wire 1 |! op_b [14] $end
$var wire 1 }! op_b [13] $end
$var wire 1 ~! op_b [12] $end
$var wire 1 !" op_b [11] $end
$var wire 1 "" op_b [10] $end
$var wire 1 #" op_b [9] $end
$var wire 1 $" op_b [8] $end
$var wire 1 %" op_b [7] $end
$var wire 1 &" op_b [6] $end
$var wire 1 '" op_b [5] $end
$var wire 1 (" op_b [4] $end
$var wire 1 )" op_b [3] $end
$var wire 1 *" op_b [2] $end
$var wire 1 +" op_b [1] $end
$var wire 1 ," op_b [0] $end
$var wire 1 -" product [47] $end
$var wire 1 ." product [46] $end
$var wire 1 /" product [45] $end
$var wire 1 0" product [44] $end
$var wire 1 1" product [43] $end
$var wire 1 2" product [42] $end
$var wire 1 3" product [41] $end
$var wire 1 4" product [40] $end
$var wire 1 5" product [39] $end
$var wire 1 6" product [38] $end
$var wire 1 7" product [37] $end
$var wire 1 8" product [36] $end
$var wire 1 9" product [35] $end
$var wire 1 :" product [34] $end
$var wire 1 ;" product [33] $end
$var wire 1 <" product [32] $end
$var wire 1 =" product [31] $end
$var wire 1 >" product [30] $end
$var wire 1 ?" product [29] $end
$var wire 1 @" product [28] $end
$var wire 1 A" product [27] $end
$var wire 1 B" product [26] $end
$var wire 1 C" product [25] $end
$var wire 1 D" product [24] $end
$var wire 1 E" product [23] $end
$var wire 1 F" product [22] $end
$var wire 1 G" product [21] $end
$var wire 1 H" product [20] $end
$var wire 1 I" product [19] $end
$var wire 1 J" product [18] $end
$var wire 1 K" product [17] $end
$var wire 1 L" product [16] $end
$var wire 1 M" product [15] $end
$var wire 1 N" product [14] $end
$var wire 1 O" product [13] $end
$var wire 1 P" product [12] $end
$var wire 1 Q" product [11] $end
$var wire 1 R" product [10] $end
$var wire 1 S" product [9] $end
$var wire 1 T" product [8] $end
$var wire 1 U" product [7] $end
$var wire 1 V" product [6] $end
$var wire 1 W" product [5] $end
$var wire 1 X" product [4] $end
$var wire 1 Y" product [3] $end
$var wire 1 Z" product [2] $end
$var wire 1 [" product [1] $end
$var wire 1 \" product [0] $end
$var wire 1 ]" product_normalised [47] $end
$var wire 1 ^" product_normalised [46] $end
$var wire 1 _" product_normalised [45] $end
$var wire 1 `" product_normalised [44] $end
$var wire 1 a" product_normalised [43] $end
$var wire 1 b" product_normalised [42] $end
$var wire 1 c" product_normalised [41] $end
$var wire 1 d" product_normalised [40] $end
$var wire 1 e" product_normalised [39] $end
$var wire 1 f" product_normalised [38] $end
$var wire 1 g" product_normalised [37] $end
$var wire 1 h" product_normalised [36] $end
$var wire 1 i" product_normalised [35] $end
$var wire 1 j" product_normalised [34] $end
$var wire 1 k" product_normalised [33] $end
$var wire 1 l" product_normalised [32] $end
$var wire 1 m" product_normalised [31] $end
$var wire 1 n" product_normalised [30] $end
$var wire 1 o" product_normalised [29] $end
$var wire 1 p" product_normalised [28] $end
$var wire 1 q" product_normalised [27] $end
$var wire 1 r" product_normalised [26] $end
$var wire 1 s" product_normalised [25] $end
$var wire 1 t" product_normalised [24] $end
$var wire 1 u" product_normalised [23] $end
$var wire 1 v" product_normalised [22] $end
$var wire 1 w" product_normalised [21] $end
$var wire 1 x" product_normalised [20] $end
$var wire 1 y" product_normalised [19] $end
$var wire 1 z" product_normalised [18] $end
$var wire 1 {" product_normalised [17] $end
$var wire 1 |" product_normalised [16] $end
$var wire 1 }" product_normalised [15] $end
$var wire 1 ~" product_normalised [14] $end
$var wire 1 !# product_normalised [13] $end
$var wire 1 "# product_normalised [12] $end
$var wire 1 ## product_normalised [11] $end
$var wire 1 $# product_normalised [10] $end
$var wire 1 %# product_normalised [9] $end
$var wire 1 &# product_normalised [8] $end
$var wire 1 '# product_normalised [7] $end
$var wire 1 (# product_normalised [6] $end
$var wire 1 )# product_normalised [5] $end
$var wire 1 *# product_normalised [4] $end
$var wire 1 +# product_normalised [3] $end
$var wire 1 ,# product_normalised [2] $end
$var wire 1 -# product_normalised [1] $end
$var wire 1 .# product_normalised [0] $end
$upscope $end
$upscope $end
$enddefinitions $end
#0
$dumpvars
b11000010101011101101111110111110 !
b1000011000011111000111101011100 "
1F
b11000010101011101101111110111110 G
b1000011000011111000111101011100 H
b11000110010001000010000111010010 I
b10111 J
b1000 K
0#
0$
0%
0E
1D
0C
0B
1A
0@
1?
1>
1=
0<
0;
0:
09
18
07
06
05
04
13
02
01
00
1/
0.
0-
1,
1+
0*
0)
0(
1'
1&
1.!
1/!
00!
01!
0:!
09!
18!
17!
06!
05!
04!
13!
02!
1C!
1B!
0A!
1@!
0?!
0>!
0=!
0<!
1;!
0Z!
1Y!
0X!
0W!
1V!
0U!
1T!
1S!
1R!
0Q!
0P!
0O!
0N!
1M!
0L!
0K!
0J!
0I!
1H!
0G!
0F!
0E!
1D!
0r!
1q!
1p!
1o!
1n!
1m!
0l!
1k!
1j!
1i!
1h!
1g!
1f!
0e!
1d!
1c!
0b!
1a!
1`!
1_!
0^!
1]!
0\!
1[!
0,"
0+"
1*"
1)"
1("
0'"
1&"
0%"
1$"
1#"
1""
1!"
0~!
0}!
0|!
1{!
1z!
1y!
1x!
1w!
0v!
0u!
0t!
1s!
0\"
0["
0Z"
1Y"
0X"
0W"
1V"
0U"
0T"
1S"
0R"
1Q"
0P"
0O"
0N"
1M"
1L"
0K"
1J"
0I"
1H"
1G"
1F"
1E"
0D"
0C"
0B"
1A"
0@"
1?"
1>"
1="
0<"
0;"
0:"
09"
18"
07"
06"
05"
04"
13"
02"
01"
00"
1/"
1."
0-"
0.#
0-#
0,#
0+#
1*#
0)#
0(#
1'#
0&#
0%#
1$#
0##
1"#
0!#
0~"
0}"
1|"
1{"
0z"
1y"
0x"
1w"
1v"
1u"
1t"
0s"
0r"
0q"
1p"
0o"
1n"
1m"
1l"
0k"
0j"
0i"
0h"
1g"
0f"
0e"
0d"
0c"
1b"
0a"
0`"
0_"
1^"
1]"
0-!
0,!
1+!
1*!
1)!
0(!
1'!
0&!
1%!
1$!
1#!
1"!
0!!
0~
0}
1|
1{
1z
1y
1x
0w
0v
0u
0t
1s
1r
0q
0p
0o
0n
1m
0l
0k
1j
1i
1h
1g
1f
0e
1d
1c
1b
1a
1`
1_
0^
1]
1\
0[
1Z
1Y
1X
0W
1V
0U
1T
0S
1R
0Q
0P
0O
0N
1M
1L
$end
#10
b1000011011010100101100010111011 G
b111011100000110001001001101111 H
b111111011011111111100010001111 I
b1000011011010100101100010111011 !
b111011100000110001001001101111 "
1-!
1,!
0)!
1(!
0%!
0#!
0"!
1!!
0|
0y
0x
1t
1p
1o
1n
0m
1k
0i
0c
0b
0a
0\
0Y
1U
0T
1S
0L
0.!
0&
1r!
0p!
0j!
0i!
0h!
0c!
0`!
1\!
0B!
1A!
1?!
1>!
1=!
1<!
0;!
1,"
1+"
0("
1'"
0$"
0""
0!"
1~!
0{!
0x!
0w!
19!
16!
15!
14!
03!
1\"
1Z"
0Y"
1X"
0V"
1T"
1R"
1P"
0L"
1K"
0J"
1I"
0H"
0G"
0F"
1D"
1C"
1B"
0A"
0?"
0="
1:"
19"
17"
16"
15"
14"
12"
10"
1-#
1+#
0*#
1)#
0'#
1%#
1##
1!#
0{"
1z"
0y"
1x"
0w"
0v"
0u"
1s"
1r"
1q"
0p"
0n"
0l"
1i"
1h"
1f"
1e"
1d"
1c"
1a"
1_"
1-
1*
1)
1(
0'
1Z!
1X!
1W!
0V!
0T!
0R!
1O!
1N!
1L!
1K!
1J!
1I!
1G!
1E!
1E
1C
1B
0A
0?
0=
1:
19
17
16
15
14
12
10
#20
b1000010001101001000010100011111 G
b1000010011111001000010100011111 H
b1000101001100100001000011101010 I
b1000010001101001000010100011111 !
b1000010011111001000010100011111 "
1)!
0(!
0'!
1%!
0$!
1#!
0!!
1|
0{
0z
1y
1x
1w
1v
1u
0t
0s
0p
0o
0n
1m
1i
0f
0d
1c
1a
0`
0_
0]
1\
0Z
1Y
0X
1W
0U
0S
1p!
0m!
0k!
1j!
1h!
0g!
0f!
0d!
1c!
0a!
1`!
0_!
1^!
0\!
0C!
0A!
0?!
0>!
0=!
0<!
1;!
1("
0'"
0&"
1$"
0#"
1""
0~!
1{!
0z!
0y!
1x!
1w!
1v!
1u!
1t!
1:!
09!
08!
06!
05!
04!
13!
0Z"
0X"
1V"
1U"
0S"
0R"
1O"
0M"
1L"
0K"
0C"
0B"
1A"
1?"
1="
0:"
09"
07"
06"
05"
04"
02"
0."
1-"
10!
0:!
19!
1.#
0-#
0+#
0)#
1(#
1'#
1&#
0%#
0$#
0z"
1y"
0x"
1u"
0s"
0r"
1o"
1n"
0i"
0g"
0f"
0e"
0d"
0b"
0a"
1`"
0^"
1.
0-
0,
0*
0)
0(
1'
0Z!
0X!
1U!
1T!
0O!
0M!
0L!
0K!
0J!
0H!
0G!
1F!
0D!
0.
1-
0E
0C
1@
1?
0:
08
07
06
05
03
02
11
0/
#30
b1000000010010011001100110011010 G
b11000001011001100011110101110001 H
b11000010001101010101000001100011 I
b1000000010010011001100110011010 !
b11000001011001100011110101110001 "
0,!
0+!
0*!
1(!
1'!
1"!
1!!
1~
0|
1z
0x
0w
1s
0r
1l
0k
0i
1d
0a
1`
1_
1[
0Y
1X
0W
0V
1U
0R
1.!
1&
0r!
0p!
1k!
0h!
1g!
1f!
1b!
0`!
1_!
0^!
0]!
1\!
1B!
0@!
0+"
0*"
0)"
1'"
1&"
1!"
1~!
1}!
0{!
1y!
0w!
0v!
09!
18!
07!
0\"
1["
1Y"
1X"
1W"
0T"
1S"
1R"
1N"
0L"
1K"
0I"
1H"
1G"
1F"
0D"
1C"
0A"
0="
16"
14"
03"
12"
0.#
1-#
1+#
1*#
1)#
0&#
1%#
1$#
1~"
0|"
1{"
0y"
1x"
1w"
1v"
0t"
1s"
0q"
0m"
1f"
1d"
0c"
1b"
0-
1,
0+
1Z!
0W!
0S!
1L!
1J!
0I!
1H!
1E
0B
0>
17
15
04
13
#40
b11000001010100100110011001100110 G
b11000010010000001010001111010111 H
b1000100000111100101001101110100 I
b11000001010100100110011001100110 !
b11000010010000001010001111010111 "
1,!
1+!
0(!
1&!
1$!
0#!
0"!
0!!
1|
0z
0y
0v
0s
1r
1i
0h
0g
1f
1e
0d
0c
1b
1a
0`
0_
1^
1]
0\
0[
1Z
0X
1W
1S
1L
0.!
0&
1p!
0o!
0n!
1m!
1l!
0k!
0j!
1i!
1h!
0g!
0f!
1e!
1d!
0c!
0b!
1a!
0_!
1^!
1A!
1+"
1*"
0'"
1%"
1#"
0""
0!"
0~!
1{!
0y!
0x!
0u!
08!
17!
0X"
0V"
1T"
0S"
0R"
0Q"
1M"
1J"
0H"
0E"
0C"
1B"
1@"
1<"
1;"
04"
13"
11"
0/"
0*#
0(#
1&#
0%#
0$#
0##
1}"
1z"
0x"
0u"
0s"
1r"
1p"
1l"
1k"
0d"
1c"
1a"
0_"
0,
1+
0Z!
0Y!
1X!
1V!
1R!
1Q!
0J!
1I!
1G!
0E!
0E
0D
1C
1A
1=
1<
05
14
12
00
#50
b0 G
b0 H
b0 I
b0 !
b0 "
0-!
0,!
0+!
0)!
0'!
0&!
0%!
0$!
0~
0|
0u
0r
0m
0l
0j
0i
0f
0e
0b
0a
0^
0]
0Z
0W
0U
0S
0M
0L
0q!
0p!
0m!
0l!
0i!
0h!
0e!
0d!
0a!
0^!
0\!
0[!
0B!
0A!
0;!
0,"
0+"
0*"
0("
0&"
0%"
0$"
0#"
0}!
0{!
0t!
0s!
19!
07!
12!
0["
0Y"
0W"
0U"
0T"
0P"
0O"
0N"
0M"
0K"
0J"
0G"
0F"
0B"
0@"
0?"
0>"
0<"
0;"
08"
06"
03"
02"
01"
00"
0-"
00!
1%
1:!
09!
0-#
0+#
0)#
0'#
0&#
0"#
0!#
0~"
0}"
0{"
0z"
0w"
0v"
0r"
0p"
0o"
0n"
0l"
0k"
0h"
0f"
0c"
0b"
0a"
0`"
0]"
0C
0A
0@
0?
0=
0<
09
07
04
03
02
01
0+
0'
0/!
0X!
0V!
0U!
0T!
0R!
0Q!
0N!
0L!
0I!
0H!
0G!
0F!
11!
0%
#60
b11000001010100100110011001100110 G
b11000001010100100110011001100110 !
1j
1i
1f
1e
1b
1a
1^
1]
1Z
1W
1U
1S
1M
1L
1.!
1B!
1<!
1q!
1p!
1m!
1l!
1i!
1h!
1e!
1d!
1a!
1^!
1\!
1[!
19!
03!
02!
#70
b1111111100000000000000000000000 G
b1111111100000000000000000000000 H
b1111111100000000000000000000000 !
b1111111100000000000000000000000 "
1t
1s
1r
1q
1p
1o
1n
1m
0j
0i
0f
0e
0b
0a
0^
0]
0Z
0W
0U
1T
1R
1Q
1P
1O
1N
0L
0.!
1#
0q!
0p!
0m!
0l!
0i!
0h!
0e!
0d!
0a!
0^!
0\!
1s!
1A!
1@!
1?!
1>!
1=!
1;!
01!
18!
17!
16!
15!
14!
12!
1."
1$
1]"
#80
b110000100010010111000001011111 G
b110000100010010111000001011111 H
b100001100100111001001011101110 I
b110000100010010111000001011111 !
b110000100010010111000001011111 "
1-!
1,!
1+!
1*!
1)!
1'!
1!!
1~
1}
1{
1x
0s
0r
0q
0p
0m
1k
1j
1i
1h
1g
1e
1_
1^
1]
1[
1X
0S
0R
0Q
0P
0M
0#
1r!
1q!
1p!
1o!
1n!
1l!
1f!
1e!
1d!
1b!
1_!
0A!
0@!
0?!
0>!
0;!
1,"
1+"
1*"
1)"
1("
1&"
1~!
1}!
1|!
1z!
1w!
11!
08!
07!
06!
05!
02!
1\"
1V"
1T"
1S"
1N"
1L"
1D"
1C"
1B"
1@"
1?"
1>"
1<"
19"
16"
15"
14"
11"
1.
1-
1,
1+
1*
1)
1(
1'
0$
1-#
1'#
1%#
1$#
1}"
1{"
1s"
1r"
1q"
1o"
1n"
1m"
1k"
1h"
1e"
1d"
1c"
1`"
0.
0-
0,
0+
0*
0)
0(
0'
1/!
1Y!
1X!
1W!
1U!
1T!
1S!
1Q!
1N!
1K!
1J!
1I!
1F!
01!
1D
1C
1B
1@
1?
1>
1<
19
16
15
14
11
1.
1-
1(
#90
b1100000101011010111100011101100 G
b1111110100101100111011010011001 H
b1111111100000000000000000000000 I
b1100000101011010111100011101100 !
b1111110100101100111011010011001 "
0,!
0+!
0'!
1&!
1$!
1#!
0{
1z
1y
0x
1w
1r
1q
1p
1m
0k
0j
0g
1f
1d
1`
1Y
1V
0O
1M
0r!
0q!
0n!
1m!
1k!
1g!
1`!
1]!
1A!
1@!
1?!
1>!
0=!
1;!
0+"
0*"
0&"
1%"
1#"
1""
0z!
1y!
1x!
0w!
1v!
18!
17!
16!
15!
04!
12!
0\"
1Z"
1Y"
0V"
0S"
1R"
1Q"
0N"
0L"
1K"
1H"
1G"
1E"
0>"
1:"
09"
18"
17"
12"
01"
1/"
1$
0-#
1+#
1*#
0'#
0$#
1##
1"#
0}"
0{"
1z"
1w"
1v"
1t"
0m"
1i"
0h"
1g"
1f"
1a"
0`"
1^"
0D
0C
0B
0@
0?
0>
0<
09
06
05
04
01
1,
1+
1*
1)
1'
1Z!
0S!
1O!
0N!
1M!
1L!
1G!
0F!
1D!
