HW2_400104867/DSD_HW2_FULL_FILE/RCA.v
`timescale 1ns/1ns 

module HA(a,b,sum,cout);
input a,b;
output reg sum,cout;

always @(*) 
  begin
   #2 
   cout = a & b;
  end
  
  always @(*) 
  begin
  #3
  sum = a ^ b;
  end
  
endmodule



module FA( 
  input a, b, Cin, 
  output S, Cout
  );  
  
  wire w1, w2, w3;    
  HA HA1(a, b, w1, w2);
  
  HA HA2(w1, Cin,S, w3);
  
  or(Cout,w2, w3);
  
endmodule  


module Adder(a,b,cin,sum,cout);
input [3:0]a,b;
input cin;
output wire [3:0]sum;
output cout;

wire cout1, cout2, cout3;

FA FA1(a[0],b[0],cin,sum[0],cout1);
FA FA2(a[1],b[1],cout1,sum[1],cout2);
FA FA3(a[2],b[2],cout2,sum[2],cout3);
FA FA4(a[3],b[3],cout3,sum[3],cout);
endmodule

HW2_400104867/DSD_HW2_FULL_FILE/TestBench.v
`timescale 1ns/1ns

module TestBench;
  
  initial begin     
  $dumpfile("waveform.vcd");     
  $dumpvars(0,TestBench);   
  end
  
  
  reg [3:0] A;
  reg [3:0] B;
  reg C_in;
  
  wire [3:0] S;
  wire C_out;

  Adder adder(A, B, C_in, S, C_out);

  initial
  begin
		A = 4'b1010; 
		B = 4'b0101; 
		C_in = 1'b1;
  end  

endmodule

HW2_400104867/DSD_HW2_FULL_FILE/waveform.vcd
$date
	Mon May 01 23:15:27 2023
$end
$version
	ModelSim Version 10.1d
$end
$timescale
	1ns
$end
$scope module TestBench $end
$var reg 4 ! A [3:0] $end
$var reg 4 " B [3:0] $end
$var reg 1 # C_in $end
$var wire 1 $ S [3] $end
$var wire 1 % S [2] $end
$var wire 1 & S [1] $end
$var wire 1 ' S [0] $end
$var wire 1 ( C_out $end
$scope module adder $end
$var wire 1 ) a [3] $end
$var wire 1 * a [2] $end
$var wire 1 + a [1] $end
$var wire 1 , a [0] $end
$var wire 1 - b [3] $end
$var wire 1 . b [2] $end
$var wire 1 / b [1] $end
$var wire 1 0 b [0] $end
$var wire 1 1 cin $end
$var wire 1 $ sum [3] $end
$var wire 1 % sum [2] $end
$var wire 1 & sum [1] $end
$var wire 1 ' sum [0] $end
$var wire 1 ( cout $end
$var wire 1 2 cout1 $end
$var wire 1 3 cout2 $end
$var wire 1 4 cout3 $end
$scope module FA1 $end
$var wire 1 , a $end
$var wire 1 0 b $end
$var wire 1 1 Cin $end
$var wire 1 ' S $end
$var wire 1 2 Cout $end
$var wire 1 5 w1 $end
$var wire 1 6 w2 $end
$var wire 1 7 w3 $end
$scope module HA1 $end
$var wire 1 , a $end
$var wire 1 0 b $end
$var reg 1 8 sum $end
$var reg 1 9 cout $end
$upscope $end
$scope module HA2 $end
$var wire 1 5 a $end
$var wire 1 1 b $end
$var reg 1 : sum $end
$var reg 1 ; cout $end
$upscope $end
$upscope $end
$scope module FA2 $end
$var wire 1 + a $end
$var wire 1 / b $end
$var wire 1 2 Cin $end
$var wire 1 & S $end
$var wire 1 3 Cout $end
$var wire 1 < w1 $end
$var wire 1 = w2 $end
$var wire 1 > w3 $end
$scope module HA1 $end
$var wire 1 + a $end
$var wire 1 / b $end
$var reg 1 ? sum $end
$var reg 1 @ cout $end
$upscope $end
$scope module HA2 $end
$var wire 1 < a $end
$var wire 1 2 b $end
$var reg 1 A sum $end
$var reg 1 B cout $end
$upscope $end
$upscope $end
$scope module FA3 $end
$var wire 1 * a $end
$var wire 1 . b $end
$var wire 1 3 Cin $end
$var wire 1 % S $end
$var wire 1 4 Cout $end
$var wire 1 C w1 $end
$var wire 1 D w2 $end
$var wire 1 E w3 $end
$scope module HA1 $end
$var wire 1 * a $end
$var wire 1 . b $end
$var reg 1 F sum $end
$var reg 1 G cout $end
$upscope $end
$scope module HA2 $end
$var wire 1 C a $end
$var wire 1 3 b $end
$var reg 1 H sum $end
$var reg 1 I cout $end
$upscope $end
$upscope $end
$scope module FA4 $end
$var wire 1 ) a $end
$var wire 1 - b $end
$var wire 1 4 Cin $end
$var wire 1 $ S $end
$var wire 1 ( Cout $end
$var wire 1 J w1 $end
$var wire 1 K w2 $end
$var wire 1 L w3 $end
$scope module HA1 $end
$var wire 1 ) a $end
$var wire 1 - b $end
$var reg 1 M sum $end
$var reg 1 N cout $end
$upscope $end
$scope module HA2 $end
$var wire 1 J a $end
$var wire 1 4 b $end
$var reg 1 O sum $end
$var reg 1 P cout $end
$upscope $end
$upscope $end
$upscope $end
$upscope $end
$enddefinitions $end
#0
$dumpvars
b1010 !
b101 "
1#
x8
x9
x:
x;
x?
x@
xA
xB
xF
xG
xH
xI
xM
xN
xO
xP
x'
x&
x%
x$
x(
x2
x3
x4
x5
x6
x7
x<
x=
x>
xC
xD
xE
xJ
xK
xL
11
10
0/
1.
0-
0,
1+
0*
1)
$end
#2
0N
0G
0@
09
0K
0D
0=
06
#3
1M
1F
1?
18
1J
1C
1<
15
#5
1;
17
12
#6
0:
0A
0'
0&
#7
1B
1>
13
#9
1I
1E
14
#10
0H
0%
#11
1P
1L
1(
#12
0O
0$
