HW3_Single_Channel_Ram_400104867/RAM.v
module Ram(
    input clk,
    input write,
    inout [15:0] data,
    input [11:0] address
);

reg [15:0] memory [0 : 2 ** 12 -1];

assign data = write ?   'hz :memory[address] ; // khorouji ro handle shod

always @(posedge clk) begin
    if (write)
        memory[address] <= data;
end

endmodule


module TestBench;
    reg clk;
    reg write;
    wire [15:0] data;
    reg [11:0] address;

    Ram ram(
        .clk(clk),
        .write(write),
        .data(data),
        .address(address)
        );

    reg [15:0] data_driver;

    assign data = write ?  data_driver : 'hz ; // vasl kardan sim be ye driver

    always #5 clk = ~clk;

    initial
    begin
    $dumpfile("Ram.vcd");
    $dumpvars(0, TestBench);
    end

    initial begin
    clk <= 1;
    {write , data_driver , address} <= 0;

    //test(a,1,c); --> mem[c] = a
    //test(a,0,c); --> read mem[c]

    test(16'd55,1'b1,12'd20);
    test(16'd70,1'b1,12'd60);
    //write

    test(16'd0,1'b0,12'd20);
    test(16'd0,1'b0,12'd60);
    //read

    test(16'd345,1'b1,12'd20);
    test(16'd0,1'b0,12'd20);
    test(16'd85,1'b1,12'd60);
    test(16'd0,1'b0,12'd60);
    //overwrite

    $stop;

    end


task test(
input [15:0] data_in,
input wr,
input [11 : 0] addr
);
begin
    #5;
    address <= addr;
    write <= wr;
    data_driver <= data_in;
    #5;
    if (wr)
        $display("data : %d write in add : %d",data,address);
    else
        $display("read data is %d from address : %d",data,address);
  
end
endtask

    
endmodule

HW3_Single_Channel_Ram_400104867/Ram.vcd
$date
	Sun May 28 15:52:19 2023
$end
$version
	ModelSim Version 2020.4
$end
$timescale
	1ns
$end

$scope module TestBench $end
$var reg 1 ! clk $end
$var reg 1 " write $end
$var wire 1 # data [15] $end
$var wire 1 $ data [14] $end
$var wire 1 % data [13] $end
$var wire 1 & data [12] $end
$var wire 1 ' data [11] $end
$var wire 1 ( data [10] $end
$var wire 1 ) data [9] $end
$var wire 1 * data [8] $end
$var wire 1 + data [7] $end
$var wire 1 , data [6] $end
$var wire 1 - data [5] $end
$var wire 1 . data [4] $end
$var wire 1 / data [3] $end
$var wire 1 0 data [2] $end
$var wire 1 1 data [1] $end
$var wire 1 2 data [0] $end
$var reg 12 3 address [11:0] $end
$var reg 16 4 data_driver [15:0] $end

$scope task test $end
$var reg 16 5 data_in [15:0] $end
$var reg 1 6 wr $end
$var reg 12 7 addr [11:0] $end
$upscope $end

$scope module ram $end
$var wire 1 8 clk $end
$var wire 1 9 write $end
$var wire 1 # data [15] $end
$var wire 1 $ data [14] $end
$var wire 1 % data [13] $end
$var wire 1 & data [12] $end
$var wire 1 ' data [11] $end
$var wire 1 ( data [10] $end
$var wire 1 ) data [9] $end
$var wire 1 * data [8] $end
$var wire 1 + data [7] $end
$var wire 1 , data [6] $end
$var wire 1 - data [5] $end
$var wire 1 . data [4] $end
$var wire 1 / data [3] $end
$var wire 1 0 data [2] $end
$var wire 1 1 data [1] $end
$var wire 1 2 data [0] $end
$var wire 1 : address [11] $end
$var wire 1 ; address [10] $end
$var wire 1 < address [9] $end
$var wire 1 = address [8] $end
$var wire 1 > address [7] $end
$var wire 1 ? address [6] $end
$var wire 1 @ address [5] $end
$var wire 1 A address [4] $end
$var wire 1 B address [3] $end
$var wire 1 C address [2] $end
$var wire 1 D address [1] $end
$var wire 1 E address [0] $end
$upscope $end
$upscope $end
$enddefinitions $end
#0
$dumpvars
1!
0"
b0 3
b0 4
b110111 5
16
b10100 7
x2
x1
x0
x/
x.
x-
x,
x+
x*
x)
x(
x'
x&
x%
x$
x#
0E
0D
0C
0B
0A
0@
0?
0>
0=
0<
0;
0:
09
18
$end
#5
0!
08
b10100 3
1"
b110111 4
1C
1A
19
12
11
10
0/
1.
1-
0,
0+
0*
0)
0(
0'
0&
0%
0$
0#
#10
1!
b1000110 5
b111100 7
18
#15
0!
08
b111100 3
b1000110 4
02
0.
0-
1,
1B
1@
#20
1!
b0 5
06
b10100 7
18
#25
0!
08
b10100 3
0"
b0 4
z2
z1
z0
z/
z.
z-
z,
z+
z*
z)
z(
z'
z&
z%
z$
z#
0B
0@
09
12
11
10
0/
1.
1-
0,
0+
0*
0)
0(
0'
0&
0%
0$
0#
#30
1!
b111100 7
18
#35
0!
08
b111100 3
1B
1@
02
0.
0-
1,
#40
1!
b101011001 5
16
b10100 7
18
#45
0!
08
b10100 3
1"
b101011001 4
x2
x1
x0
x/
x.
x*
0B
0@
19
12
01
00
1/
1.
1*
#50
1!
b0 5
06
18
#55
0!
08
0"
b0 4
z2
z1
z0
z/
z.
z-
z,
z+
z*
z)
z(
z'
z&
z%
z$
z#
09
12
01
00
1/
1.
0-
1,
0+
1*
0)
0(
0'
0&
0%
0$
0#
#60
1!
b1010101 5
16
b111100 7
18
#65
0!
08
b111100 3
1"
b1010101 4
x0
x/
x*
1B
1@
19
10
0/
0*
#70
1!
b0 5
06
18
#75
0!
08
0"
b0 4
z2
z1
z0
z/
z.
z-
z,
z+
z*
z)
z(
z'
z&
z%
z$
z#
09
12
01
10
0/
1.
0-
1,
0+
0*
0)
0(
0'
0&
0%
0$
0#
